clashinfo/__init__.py
clashinfo/coc.py
clashinfo/cr.py
clashinfo-0.1.1.dist-info/LICENSE
clashinfo-0.1.1.dist-info/METADATA
clashinfo-0.1.1.dist-info/WHEEL
clashinfo-0.1.1.dist-info/top_level.txt
clashinfo-0.1.1.dist-info/RECORD
